{
  "name": "Shortest paths from non-Tier Zero user accounts to Tier Zero",
  "guid": "8b61bf34-5256-47e5-a5a8-370e8ddc3f90",
  "prebuilt": false,
  "platforms": "Active Directory",
  "category": "Shortest Paths",
  "description": "WARNING! MANY-TO-MANY SHORTEST PATH QUERIES USE EXCESSIVE SYSTEM RESOURCES AND TYPICALLY WILL NOT COMPLETE",
  "query": "// MANY TO MANY SHORTEST PATH QUERIES USE EXCESSIVE SYSTEM RESOURCES AND TYPICALLY WILL NOT COMPLETE\nMATCH p=shortestPath((s:User)-[:AD_ATTACK_PATHS*1..]->(t:Base))\nWHERE s<>t\nAND NOT ((s:Tag_Tier_Zero) OR COALESCE(s.system_tags, '') CONTAINS 'admin_tier_0')\nAND ((t:Tag_Tier_Zero) OR COALESCE(t.system_tags, '') CONTAINS 'admin_tier_0')\nRETURN p\nLIMIT 1000",
  "revision": 1,
  "resources": null,
  "acknowledgements": null
}